monkeybread/__init__.py
monkeybread/calc/._kernel_density.py.swp
monkeybread/calc/__init__.py
monkeybread/calc/_cell_density.py
monkeybread/calc/_cell_neighbors.py
monkeybread/calc/_ligand_receptor.py
monkeybread/calc/_neighborhood_profile.py
monkeybread/calc/_number_neighbors.py
monkeybread/calc/_shortest_distances.py
monkeybread/plot/._embedding_other.py.swn
monkeybread/plot/._embedding_other.py.swo
monkeybread/plot/._embedding_other.py.swp
monkeybread/plot/._kernel_density.py.swo
monkeybread/plot/._kernel_density.py.swp
monkeybread/plot/._ligand_receptor.py.swp
monkeybread/plot/._neighborhood_profile.py.swp
monkeybread/plot/__init__.py
monkeybread/plot/_cell_density.py
monkeybread/plot/_cell_neighbors.py
monkeybread/plot/_embedding_other.py
monkeybread/plot/_ligand_receptor.py
monkeybread/plot/_ligand_receptor_future.py
monkeybread/plot/_neighborhood_profile.py
monkeybread/plot/_number_neighbors.py
monkeybread/plot/_shortest_distances.py
monkeybread/stat/._ligand_receptor.py.swp
monkeybread/stat/__init__.py
monkeybread/stat/_cell_neighbors.py
monkeybread/stat/_ligand_receptor.py
monkeybread/stat/_shortest_distances.py
monkeybread/util/__init__.py
monkeybread/util/_load_merscope.py
monkeybread/util/_neighbor_count.py
monkeybread/util/_omnipath.py
monkeybread/util/_subset_cells.py
monkeybread-1.0.3.dist-info/METADATA
monkeybread-1.0.3.dist-info/WHEEL
monkeybread-1.0.3.dist-info/licenses/LICENSE
monkeybread-1.0.3.dist-info/RECORD
