Metadata-Version: 2.1
Name: monkeybread
Version: 1.0.3
Summary: Analyze cellular niches in single-cell spatial transcriptomics data
Project-URL: Documentation, https://monkeybread.readthedocs.io/
Project-URL: Source, https://github.com/immunitastx/monkeybread
Project-URL: Home-page, https://github.com/immunitastx/monkeybread
Author: Immunitas Therapeutics
Maintainer-email: Immunitas Therapeutics <mbernstein@immunitastx.com>, Immunitas Therapeutics <mtang@immunitastx.com>
License: MIT License
License-File: LICENSE
Requires-Python: >=3.8
Requires-Dist: anndata>=0.7.4
Requires-Dist: matplotlib>=3.4
Requires-Dist: numpy>=1.17.0
Requires-Dist: omnipath>=1.0.7
Requires-Dist: pandas>=1.0
Requires-Dist: scanpy>=1.9.0
Requires-Dist: scikit-learn>=0.22
Requires-Dist: seaborn
Requires-Dist: session-info
Requires-Dist: tqdm
Requires-Dist: tqdm>=4.64.1
Provides-Extra: dev
Requires-Dist: bump2version; extra == 'dev'
Requires-Dist: pre-commit; extra == 'dev'
Provides-Extra: doc
Requires-Dist: ipykernel; extra == 'doc'
Requires-Dist: ipython==8.4.0; extra == 'doc'
Requires-Dist: myst-nb; extra == 'doc'
Requires-Dist: sphinx-autodoc-typehints; extra == 'doc'
Requires-Dist: sphinx-book-theme>=0.3.3; extra == 'doc'
Requires-Dist: sphinx-copybutton; extra == 'doc'
Requires-Dist: sphinx>=4; extra == 'doc'
Requires-Dist: sphinxcontrib-bibtex>=1.0.0; extra == 'doc'
Provides-Extra: test
Requires-Dist: pytest; extra == 'test'
Requires-Dist: pytest-cov; extra == 'test'
Requires-Dist: pytest-nunit; extra == 'test'
